Workbook

Sheet Flat benefit
G1: Projection Year -> | H1: 1 | I1: =H1+1 -> 2 | J1: =I1+1 -> 3 | K1: =J1+1 -> 4 | L1: =K1+1 -> 5 | M1: =L1+1 -> 6 | N1: =M1+1 -> 7 | O1: =N1+1 -> 8 | P1: =O1+1 -> 9 | ... AT1: =AS1+1 -> 39
G2: NEU's Age -> | H2: 27 | I2: =H2+1 -> 28 | J2: =I2+1 -> 29 | K2: =J2+1 -> 30 | L2: =K2+1 -> 31 | M2: =L2+1 -> 32 | N2: =M2+1 -> 33 | O2: =N2+1 -> 34 | P2: =O2+1 -> 35 | ... AT2: =AS2+1 -> 65
I3: Projected
H4: 2017 | I4: =H4+1 -> 2018 | J4: =I4+1 -> 2019 | K4: =J4+1 -> 2020 | L4: =K4+1 -> 2021 | M4: =L4+1 -> 2022 | N4: =M4+1 -> 2023 | O4: =N4+1 -> 2024 | P4: =O4+1 -> 2025 | ... AT4: =AS4+1 -> 2055
B6: Salary Information
B7: Salary (NEU) / Gender: M | H7: 120000 | I7: =H7*(1+$I$25) -> 124800 | J7: =I7*(1+$I$25) -> 129792 | K7: =J7*(1+$I$25) -> 134983.68 | L7: =K7*(1+$I$25) -> 140383.03 | M7: =L7*(1+$I$25) -> 145998.35 | N7: =M7*(1+$I$25) -> 151838.28 | O7: =N7*(1+$I$25) -> 157911.81 | P7: =O7*(1+$I$25) -> 164228.29 | ... AT7: =AS7*(1+$I$25) -> 532657.61
B9: Life Insurance Calculation
B10: Benefit Flat Amount | H10: 60000 | I10: 60000 | J10: 60000 | K10: 60000 | L10: 60000 | M10: 60000 | N10: 60000 | O10: 60000 | P10: 60000 | Q10: 60000 | R10: 60000 | S10: 60000 | T10: 60000 | U10: 60000 | V10: 60000 | W10: 60000 | X10: 60000 | Y10: 60000 | Z10: 60000 | AA10: 60000 | AB10: 60000 | AC10: 60000 | AD10: 60000 | AE10: 60000 | AF10: 60000 | AG10: 60000 | AH10: 60000 | AI10: 60000 | AJ10: 60000 | AK10: 60000 | AL10: 60000 | AM10: 60000 | AN10: 60000 | AO10: 60000 | AP10: 60000 | AQ10: 60000 | AR10: 60000 | AS10: 60000 | AT10: 60000
B11: Benefit as % of Salary | H11: =H7*$H$27 -> 180000 | I11: =I7*$H$27 -> 187200 | J11: =J7*$H$27 -> 194688 | K11: =K7*$H$27 -> 202475.52 | L11: =L7*$H$27 -> 210574.54 | M11: =M7*$H$27 -> 218997.52 | N11: =N7*$H$27 -> 227757.42 | O11: =O7*$H$27 -> 236867.72 | ... AT11: =AT7*$H$27 -> 798986.42
B12: Total Benefit | H12: =H10 -> 60000 | I12: =I10 -> 60000 | J12: =J10 -> 60000 | K12: =K10 -> 60000 | L12: =L10 -> 60000 | M12: =M10 -> 60000 | N12: =N10 -> 60000 | O12: =O10 -> 60000 | ... AT12: =AT10 -> 60000
B13: qx: Probability of dying within one year | H13: =_xlfn.XLOOKUP(H2,'Mortality Table'!$A:$A,'Mortality Table'!$B:$B,"Not found") -> 0.001363 | I13: =_xlfn.XLOOKUP(I2,'Mortality Table'!$A:$A,'Mortality Table'!$B:$B,"Not found") -> 0.001391 | J13: =_xlfn.XLOOKUP(J2,'Mortality Table'!$A:$A,'Mortality Table'!$B:$B,"Not found") -> 0.001427 | K13: =_xlfn.XLOOKUP(K2,'Mortality Table'!$A:$A,'Mortality Table'!$B:$B,"Not found") -> 0.001467 | L13: =_xlfn.XLOOKUP(L2,'Mortality Table'!$A:$A,'Mortality Table'!$B:$B,"Not found") -> 0.001505 | M13: =_xlfn.XLOOKUP(M2,'Mortality Table'!$A:$A,'Mortality Table'!$B:$B,"Not found") -> 0.001541 | N13: =_xlfn.XLOOKUP(N2,'Mortality Table'!$A:$A,'Mortality Table'!$B:$B,"Not found") -> 0.001573 | O13: =_xlfn.XLOOKUP(O2,'Mortality Table'!$A:$A,'Mortality Table'!$B:$B,"Not found") -> 0.001606 | ... AT13: =_xlfn.XLOOKUP(AT2,'Mortality Table'!$A:$A,'Mortality Table'!$B:$B,"Not found") -> 0.015852
B14: px: Probability of surviving within one year | H14: =1-H13 -> 0.998637 | I14: =1-I13 -> 0.998609 | J14: =1-J13 -> 0.998573 | K14: =1-K13 -> 0.998533 | L14: =1-L13 -> 0.998495 | M14: =1-M13 -> 0.998459 | N14: =1-N13 -> 0.998427 | O14: =1-O13 -> 0.998394 | ... AT14: =1-AT13 -> 0.984148
B15: Probability of surviving up to beginning of projection year then dying within one year | H15: =H13 -> 0.001363 | I15: =PRODUCT(H14)*I13 -> 0.0013891041 | J15: =PRODUCT($H$14:I14)*J13 -> 0.0014230727 | K15: =PRODUCT($H$14:J14)*K13 -> 0.001460875 | L15: =PRODUCT($H$14:K14)*L13 -> 0.0014965177 | M15: =PRODUCT($H$14:L14)*M13 -> 0.0015300087 | N15: =PRODUCT($H$14:M14)*N13 -> 0.0015593738 | O15: =PRODUCT($H$14:N14)*O13 -> 0.0015895835 | P15: =PRODUCT($H$14:O14)*P13 -> 0.0016285346 | Q15: =PRODUCT($H$14:P14)*Q13 -> 0.0016810981 | ... AT15: =PRODUCT($H$14:AS14)*AT13 -> 0.013061701
B16: Expected Benefit if died in projection year | H16: =H15*H10 -> 81.78 | I16: =I15*I10 -> 83.346244 | J16: =J15*J10 -> 85.384365 | K16: =K15*K10 -> 87.652501 | L16: =L15*L10 -> 89.791065 | M16: =M15*M10 -> 91.800523 | N16: =N15*N10 -> 93.562426 | O16: =O15*O10 -> 95.375013 | ... AT16: =AT15*AT10 -> 783.70208
B17: Present Value Factor | H17: =(1+$H$29)^(-H1) -> 0.95238095 | I17: =(1+$H$29)^(-I1) -> 0.90702948 | J17: =(1+$H$29)^(-J1) -> 0.8638376 | K17: =(1+$H$29)^(-K1) -> 0.82270247 | L17: =(1+$H$29)^(-L1) -> 0.78352617 | M17: =(1+$H$29)^(-M1) -> 0.7462154 | N17: =(1+$H$29)^(-N1) -> 0.71068133 | O17: =(1+$H$29)^(-O1) -> 0.67683936 | ... AT17: =(1+$H$29)^(-AT1) -> 0.14914797
B18: Expected Benefit discounted back to Present Value | H18: =H17*H16 -> 77.885714 | I18: =I17*I16 -> 75.5975 | J18: =J17*J16 -> 73.758225 | K18: =K17*K16 -> 72.111929 | L18: =L17*L16 -> 70.353649 | M18: =M17*M16 -> 68.502963 | N18: =N17*N16 -> 66.493069 | O18: =O17*O16 -> 64.553563 | ... AT18: =AT17*AT16 -> 116.88757
B20: Life Insurance Premium Required | G20: =SUM(H18:AT18) -> 3307.2091
B23: Actuarial Assumptions:
C25: Salary Growth | I25: 0.04
A26: Choose | C26: Benefit Flat Amount | H26: 60000
A27: Choose | C27: Benefit % of Salary | H27: 1.5
C28: qx: Probability of dying within one year | H28: Lookup values against "Mortality Table" tab
C29: Present Value Interest Rate | H29: 0.05

Sheet Task 3 - Summary
A1: Option A: Flat Benefit Plan at $1,000 premium
B2: Required Flat Benefit Amount: | G2: ='Task 3 - Flat'!H26 -> 18142.185
A3: Option B: % of Salary Plan at $1,000 premium
B4: Required % of Salary: | G4: ='Task 3 - %'!H27 -> 0.059588509
B5: In dollar terms at age 27 salary: | G5: ='Task 3 - %'!H11 -> 7150.6211
B6: In dollar terms at age 65 salary: | G6: ='Task 3 - %'!AT12 -> 31740.273
A8: RECOMMENDATION:
B9: NEU should choose the % of Salary plan at ~5.96% of salary (~$7,151 benefit at age 27).
B10: This gives him a benefit that grows with his salary (inflation protection),
B11: whereas the flat plan would only pay $18,142.

Sheet Task 3 - Flat
G1: Projection Year -> | H1: 1 | I1: =H1+1 -> 2 | J1: =I1+1 -> 3 | K1: =J1+1 -> 4 | L1: =K1+1 -> 5 | M1: =L1+1 -> 6 | N1: =M1+1 -> 7 | O1: =N1+1 -> 8 | P1: =O1+1 -> 9 | ... AT1: =AS1+1 -> 39
G2: NEU's Age -> | H2: 27 | I2: =H2+1 -> 28 | J2: =I2+1 -> 29 | K2: =J2+1 -> 30 | L2: =K2+1 -> 31 | M2: =L2+1 -> 32 | N2: =M2+1 -> 33 | O2: =N2+1 -> 34 | P2: =O2+1 -> 35 | ... AT2: =AS2+1 -> 65
I3: Projected
H4: 2017 | I4: =H4+1 -> 2018 | J4: =I4+1 -> 2019 | K4: =J4+1 -> 2020 | L4: =K4+1 -> 2021 | M4: =L4+1 -> 2022 | N4: =M4+1 -> 2023 | O4: =N4+1 -> 2024 | P4: =O4+1 -> 2025 | ... AT4: =AS4+1 -> 2055
B6: Salary Information
B7: Salary (NEU) / Gender: M | H7: 120000 | I7: =H7*(1+$I$25) -> 124800 | J7: =I7*(1+$I$25) -> 129792 | K7: =J7*(1+$I$25) -> 134983.68 | L7: =K7*(1+$I$25) -> 140383.03 | M7: =L7*(1+$I$25) -> 145998.35 | N7: =M7*(1+$I$25) -> 151838.28 | O7: =N7*(1+$I$25) -> 157911.81 | P7: =O7*(1+$I$25) -> 164228.29 | ... AT7: =AS7*(1+$I$25) -> 532657.61
B9: Life Insurance Calculation
B10: Benefit Flat Amount | H10: 18142.185 | I10: =H10 -> 18142.185 | J10: =I10 -> 18142.185 | K10: =J10 -> 18142.185 | L10: =K10 -> 18142.185 | M10: =L10 -> 18142.185 | N10: =M10 -> 18142.185 | O10: =N10 -> 18142.185 | P10: =O10 -> 18142.185 | ... AT10: =AS10 -> 18142.185
B11: Benefit as % of Salary | H11: =H7*$H$27 -> 180000 | I11: =I7*$H$27 -> 187200 | J11: =J7*$H$27 -> 194688 | K11: =K7*$H$27 -> 202475.52 | L11: =L7*$H$27 -> 210574.54 | M11: =M7*$H$27 -> 218997.52 | N11: =N7*$H$27 -> 227757.42 | O11: =O7*$H$27 -> 236867.72 | ... AT11: =AT7*$H$27 -> 798986.42
B12: Total Benefit (flat) | H12: =H10 -> 18142.185 | I12: =I10 -> 18142.185 | J12: =J10 -> 18142.185 | K12: =K10 -> 18142.185 | L12: =L10 -> 18142.185 | M12: =M10 -> 18142.185 | N12: =N10 -> 18142.185 | O12: =O10 -> 18142.185 | ... AT12: =AT10 -> 18142.185
B13: qx: Probability of dying within one year | H13: =_xlfn.XLOOKUP(H2,'Mortality Table'!$A:$A,'Mortality Table'!$B:$B,"Not found") -> 0.001363 | I13: =_xlfn.XLOOKUP(I2,'Mortality Table'!$A:$A,'Mortality Table'!$B:$B,"Not found") -> 0.001391 | J13: =_xlfn.XLOOKUP(J2,'Mortality Table'!$A:$A,'Mortality Table'!$B:$B,"Not found") -> 0.001427 | K13: =_xlfn.XLOOKUP(K2,'Mortality Table'!$A:$A,'Mortality Table'!$B:$B,"Not found") -> 0.001467 | L13: =_xlfn.XLOOKUP(L2,'Mortality Table'!$A:$A,'Mortality Table'!$B:$B,"Not found") -> 0.001505 | M13: =_xlfn.XLOOKUP(M2,'Mortality Table'!$A:$A,'Mortality Table'!$B:$B,"Not found") -> 0.001541 | N13: =_xlfn.XLOOKUP(N2,'Mortality Table'!$A:$A,'Mortality Table'!$B:$B,"Not found") -> 0.001573 | O13: =_xlfn.XLOOKUP(O2,'Mortality Table'!$A:$A,'Mortality Table'!$B:$B,"Not found") -> 0.001606 | ... AT13: =_xlfn.XLOOKUP(AT2,'Mortality Table'!$A:$A,'Mortality Table'!$B:$B,"Not found") -> 0.015852
B14: px: Probability of surviving within one year | H14: =1-H13 -> 0.998637 | I14: =1-I13 -> 0.998609 | J14: =1-J13 -> 0.998573 | K14: =1-K13 -> 0.998533 | L14: =1-L13 -> 0.998495 | M14: =1-M13 -> 0.998459 | N14: =1-N13 -> 0.998427 | O14: =1-O13 -> 0.998394 | ... AT14: =1-AT13 -> 0.984148
B15: Probability of surviving up to beginning of projection year then dying within one year | H15: =H13 -> 0.001363 | I15: =PRODUCT(H14)*I13 -> 0.0013891041 | J15: =PRODUCT($H$14:I14)*J13 -> 0.0014230727 | K15: =PRODUCT($H$14:J14)*K13 -> 0.001460875 | L15: =PRODUCT($H$14:K14)*L13 -> 0.0014965177 | M15: =PRODUCT($H$14:L14)*M13 -> 0.0015300087 | N15: =PRODUCT($H$14:M14)*N13 -> 0.0015593738 | O15: =PRODUCT($H$14:N14)*O13 -> 0.0015895835 | P15: =PRODUCT($H$14:O14)*P13 -> 0.0016285346 | Q15: =PRODUCT($H$14:P14)*Q13 -> 0.0016810981 | ... AT15: =PRODUCT($H$14:AS14)*AT13 -> 0.013061701
B16: Expected Benefit if died in projection year | H16: =H15*H10 -> 24.727798 | I16: =I15*I10 -> 25.201383 | J16: =J15*J10 -> 25.817649 | K16: =K15*K10 -> 26.503465 | L16: =L15*L10 -> 27.150102 | M16: =M15*M10 -> 27.757701 | N16: =N15*N10 -> 28.290448 | O16: =O15*O10 -> 28.838519 | ... AT16: =AT15*AT10 -> 236.9678
B17: Present Value Factor | H17: =(1+$H$29)^(-H1) -> 0.95238095 | I17: =(1+$H$29)^(-I1) -> 0.90702948 | J17: =(1+$H$29)^(-J1) -> 0.8638376 | K17: =(1+$H$29)^(-K1) -> 0.82270247 | L17: =(1+$H$29)^(-L1) -> 0.78352617 | M17: =(1+$H$29)^(-M1) -> 0.7462154 | N17: =(1+$H$29)^(-N1) -> 0.71068133 | O17: =(1+$H$29)^(-O1) -> 0.67683936 | ... AT17: =(1+$H$29)^(-AT1) -> 0.14914797
B18: Expected Benefit discounted back to Present Value | H18: =H17*H16 -> 23.550284 | I18: =I17*I16 -> 22.858397 | J18: =J17*J16 -> 22.302256 | K18: =K17*K16 -> 21.804466 | L18: =L17*L16 -> 21.272815 | M18: =M17*M16 -> 20.713224 | N18: =N17*N16 -> 20.105493 | O18: =O17*O16 -> 19.519045 | ... AT18: =AT17*AT16 -> 35.343266
B20: Life Insurance Premium Required | G20: =SUM(H18:AT18) -> 1000
B23: Actuarial Assumptions:
C25: Salary Growth | I25: 0.04
A26: Choose | C26: Benefit Flat Amount | H26: =H10 -> 18142.185
A27: Choose | C27: Benefit % of Salary | H27: 1.5
C28: qx: Probability of dying within one year | H28: Lookup values against "Mortality Table" tab
C29: Present Value Interest Rate | H29: 0.05
B32: Task 3: Design a product with $1000 premium
C33: Sử dụng solver với constrain premium = $1000 để thay đổi flat benefit amount, ta có flat amount mới = $18142

Sheet Task 3 - %
G1: Projection Year -> | H1: 1 | I1: =H1+1 -> 2 | J1: =I1+1 -> 3 | K1: =J1+1 -> 4 | L1: =K1+1 -> 5 | M1: =L1+1 -> 6 | N1: =M1+1 -> 7 | O1: =N1+1 -> 8 | P1: =O1+1 -> 9 | ... AT1: =AS1+1 -> 39
G2: NEU's Age -> | H2: 27 | I2: =H2+1 -> 28 | J2: =I2+1 -> 29 | K2: =J2+1 -> 30 | L2: =K2+1 -> 31 | M2: =L2+1 -> 32 | N2: =M2+1 -> 33 | O2: =N2+1 -> 34 | P2: =O2+1 -> 35 | ... AT2: =AS2+1 -> 65
I3: Projected
H4: 2017 | I4: =H4+1 -> 2018 | J4: =I4+1 -> 2019 | K4: =J4+1 -> 2020 | L4: =K4+1 -> 2021 | M4: =L4+1 -> 2022 | N4: =M4+1 -> 2023 | O4: =N4+1 -> 2024 | P4: =O4+1 -> 2025 | ... AT4: =AS4+1 -> 2055
B6: Salary Information
B7: Salary (NEU) / Gender: M | H7: 120000 | I7: =H7*(1+$I$25) -> 124800 | J7: =I7*(1+$I$25) -> 129792 | K7: =J7*(1+$I$25) -> 134983.68 | L7: =K7*(1+$I$25) -> 140383.03 | M7: =L7*(1+$I$25) -> 145998.35 | N7: =M7*(1+$I$25) -> 151838.28 | O7: =N7*(1+$I$25) -> 157911.81 | P7: =O7*(1+$I$25) -> 164228.29 | ... AT7: =AS7*(1+$I$25) -> 532657.61
B9: Life Insurance Calculation
B10: Benefit Flat Amount | H10: 60000 | I10: 60000 | J10: 60000 | K10: 60000 | L10: 60000 | M10: 60000 | N10: 60000 | O10: 60000 | P10: 60000 | Q10: 60000 | R10: 60000 | S10: 60000 | T10: 60000 | U10: 60000 | V10: 60000 | W10: 60000 | X10: 60000 | Y10: 60000 | Z10: 60000 | AA10: 60000 | AB10: 60000 | AC10: 60000 | AD10: 60000 | AE10: 60000 | AF10: 60000 | AG10: 60000 | AH10: 60000 | AI10: 60000 | AJ10: 60000 | AK10: 60000 | AL10: 60000 | AM10: 60000 | AN10: 60000 | AO10: 60000 | AP10: 60000 | AQ10: 60000 | AR10: 60000 | AS10: 60000 | AT10: 60000
B11: Benefit as % of Salary | H11: =H7*$H$27 -> 7150.6211 | I11: =I7*$H$27 -> 7436.646 | J11: =J7*$H$27 -> 7734.1118 | K11: =K7*$H$27 -> 8043.4763 | L11: =L7*$H$27 -> 8365.2153 | M11: =M7*$H$27 -> 8699.824 | N11: =N7*$H$27 -> 9047.8169 | O11: =O7*$H$27 -> 9409.7296 | ... AT11: =AT7*$H$27 -> 31740.273
B12: Total Benefit (%) | H12: =H11 -> 7150.6211 | I12: =I11 -> 7436.646 | J12: =J11 -> 7734.1118 | K12: =K11 -> 8043.4763 | L12: =L11 -> 8365.2153 | M12: =M11 -> 8699.824 | N12: =N11 -> 9047.8169 | O12: =O11 -> 9409.7296 | ... AT12: =AT11 -> 31740.273
B13: qx: Probability of dying within one year | H13: =_xlfn.XLOOKUP(H2,'Mortality Table'!$A:$A,'Mortality Table'!$B:$B,"Not found") -> 0.001363 | I13: =_xlfn.XLOOKUP(I2,'Mortality Table'!$A:$A,'Mortality Table'!$B:$B,"Not found") -> 0.001391 | J13: =_xlfn.XLOOKUP(J2,'Mortality Table'!$A:$A,'Mortality Table'!$B:$B,"Not found") -> 0.001427 | K13: =_xlfn.XLOOKUP(K2,'Mortality Table'!$A:$A,'Mortality Table'!$B:$B,"Not found") -> 0.001467 | L13: =_xlfn.XLOOKUP(L2,'Mortality Table'!$A:$A,'Mortality Table'!$B:$B,"Not found") -> 0.001505 | M13: =_xlfn.XLOOKUP(M2,'Mortality Table'!$A:$A,'Mortality Table'!$B:$B,"Not found") -> 0.001541 | N13: =_xlfn.XLOOKUP(N2,'Mortality Table'!$A:$A,'Mortality Table'!$B:$B,"Not found") -> 0.001573 | O13: =_xlfn.XLOOKUP(O2,'Mortality Table'!$A:$A,'Mortality Table'!$B:$B,"Not found") -> 0.001606 | ... AT13: =_xlfn.XLOOKUP(AT2,'Mortality Table'!$A:$A,'Mortality Table'!$B:$B,"Not found") -> 0.015852
B14: px: Probability of surviving within one year | H14: =1-H13 -> 0.998637 | I14: =1-I13 -> 0.998609 | J14: =1-J13 -> 0.998573 | K14: =1-K13 -> 0.998533 | L14: =1-L13 -> 0.998495 | M14: =1-M13 -> 0.998459 | N14: =1-N13 -> 0.998427 | O14: =1-O13 -> 0.998394 | ... AT14: =1-AT13 -> 0.984148
B15: Probability of surviving up to beginning of projection year then dying within one year | H15: =H13 -> 0.001363 | I15: =PRODUCT(H14)*I13 -> 0.0013891041 | J15: =PRODUCT($H$14:I14)*J13 -> 0.0014230727 | K15: =PRODUCT($H$14:J14)*K13 -> 0.001460875 | L15: =PRODUCT($H$14:K14)*L13 -> 0.0014965177 | M15: =PRODUCT($H$14:L14)*M13 -> 0.0015300087 | N15: =PRODUCT($H$14:M14)*N13 -> 0.0015593738 | O15: =PRODUCT($H$14:N14)*O13 -> 0.0015895835 | P15: =PRODUCT($H$14:O14)*P13 -> 0.0016285346 | Q15: =PRODUCT($H$14:P14)*Q13 -> 0.0016810981 | ... AT15: =PRODUCT($H$14:AS14)*AT13 -> 0.013061701
B16: Expected Benefit if died in projection year | H16: =H15*H12 -> 9.7462966 | I16: =I15*I12 -> 10.330275 | J16: =J15*J12 -> 11.006204 | K16: =K15*K12 -> 11.750514 | L16: =L15*L12 -> 12.518693 | M16: =M15*M12 -> 13.310806 | N16: =N15*N12 -> 14.108928 | O16: =O15*O12 -> 14.957551 | ... AT16: =AT15*AT12 -> 414.58197
B17: Present Value Factor | H17: =(1+$H$29)^(-H1) -> 0.95238095 | I17: =(1+$H$29)^(-I1) -> 0.90702948 | J17: =(1+$H$29)^(-J1) -> 0.8638376 | K17: =(1+$H$29)^(-K1) -> 0.82270247 | L17: =(1+$H$29)^(-L1) -> 0.78352617 | M17: =(1+$H$29)^(-M1) -> 0.7462154 | N17: =(1+$H$29)^(-N1) -> 0.71068133 | O17: =(1+$H$29)^(-O1) -> 0.67683936 | ... AT17: =(1+$H$29)^(-AT1) -> 0.14914797
B18: Expected Benefit discounted back to Present Value | H18: =H17*H16 -> 9.2821872 | I18: =I17*I16 -> 9.3698641 | J18: =J17*J16 -> 9.5075726 | K18: =K17*K16 -> 9.6671766 | L18: =L17*L16 -> 9.8087237 | M18: =M17*M16 -> 9.9327287 | N18: =N17*N16 -> 10.026952 | O18: =O17*O16 -> 10.12386 | ... AT18: =AT17*AT16 -> 61.834058
B20: Life Insurance Premium Required | G20: =SUM(H18:AT18) -> 1000
B23: Actuarial Assumptions:
C25: Salary Growth | I25: 0.04
A26: Choose | C26: Benefit Flat Amount | H26: 60000
A27: Choose | C27: Benefit % of Salary | H27: 0.059588509
C28: qx: Probability of dying within one year | H28: Lookup values against "Mortality Table" tab
C29: Present Value Interest Rate | H29: 0.05
B32: Task 3: Design a product with $1000 premium
C33: Sử dụng solver với constrain premium = $1000 để thay đổi % salary, ta có % mới = 5.96%

Sheet Mortality Table
E1: Source: Social Security Administration Actuarial Life Table
A2: Period Life Table, 2013 | E2: https://www.ssa.gov/oact/STATS/table4c6.html
A3: Exact | B3: Male | C3: Female
A4: age | B4: Death probability | C4: Death probability
A5: 0 | B5: 0.006519 | C5: 0.005377
A6: 1 | B6: 0.000462 | C6: 0.000379
A7: 2 | B7: 0.000291 | C7: 0.000221
A8: 3 | B8: 0.000209 | C8: 0.000162
A9: 4 | B9: 0.000176 | C9: 0.000133
A10: 5 | B10: 0.000159 | C10: 0.000119
A11: 6 | B11: 0.000146 | C11: 0.000109
A12: 7 | B12: 0.000133 | C12: 0.000101
A13: 8 | B13: 0.000118 | C13: 9.6e-05
A14: 9 | B14: 0.000102 | C14: 9.3e-05
A15: 10 | B15: 9.1e-05 | C15: 9.4e-05
A16: 11 | B16: 9.6e-05 | C16: 0.0001
... A124: 119 | B124: 0.893381 | C124: 0.893381
